easyvcf/command_line.py
easyvcf/converter.py
easyvcf-1.0.dist-info/LICENSE.txt
easyvcf-1.0.dist-info/METADATA
easyvcf-1.0.dist-info/WHEEL
easyvcf-1.0.dist-info/entry_points.txt
easyvcf-1.0.dist-info/top_level.txt
easyvcf-1.0.dist-info/RECORD
