Metadata-Version: 2.1
Name: easyvcf
Version: 1.0
Summary: Easily convert data in csv to vcf contacts!
Home-page: http://github.com/dogumer/easyvcf
Author: Dogukan Meral
Author-email: dogukan.meral@yahoo.com
License: MIT
Keywords: python utaa thkü ieee easyvcf vcf csv convert dogukan meral
Classifier: License :: OSI Approved :: MIT License
Classifier: Operating System :: Microsoft :: Windows
Classifier: Operating System :: POSIX :: Linux
Classifier: Operating System :: MacOS
Classifier: Programming Language :: Python :: 3.8
Classifier: Topic :: Communications
Classifier: Topic :: Database
Classifier: Topic :: Office/Business :: Groupware
Classifier: Topic :: Utilities
License-File: LICENSE.txt
